slow_start_rewatch/__init__.py
slow_start_rewatch/__main__.py
slow_start_rewatch/app.py
slow_start_rewatch/config.py
slow_start_rewatch/config_default.yml
slow_start_rewatch/config_storage.py
slow_start_rewatch/exceptions.py
slow_start_rewatch/http_server/__init__.py
slow_start_rewatch/http_server/http_server.py
slow_start_rewatch/http_server/static/css/bootstrap.css
slow_start_rewatch/http_server/static/css/bootstrap.css.map
slow_start_rewatch/http_server/static/css/bootstrap.min.css
slow_start_rewatch/http_server/static/css/bootstrap.min.css.map
slow_start_rewatch/http_server/static/css/style.css
slow_start_rewatch/http_server/static/favicon.ico
slow_start_rewatch/http_server/static/img/access-denied.gif
slow_start_rewatch/http_server/static/img/access-denied.mp4
slow_start_rewatch/http_server/static/img/access-denied.webm
slow_start_rewatch/http_server/static/img/authorization-error.gif
slow_start_rewatch/http_server/static/img/authorization-error.mp4
slow_start_rewatch/http_server/static/img/authorization-error.webm
slow_start_rewatch/http_server/static/img/favicon-16x16.png
slow_start_rewatch/http_server/static/img/favicon-32x32.png
slow_start_rewatch/http_server/static/img/http-error.gif
slow_start_rewatch/http_server/static/img/http-error.mp4
slow_start_rewatch/http_server/static/img/http-error.webm
slow_start_rewatch/http_server/static/img/success.gif
slow_start_rewatch/http_server/static/img/success.mp4
slow_start_rewatch/http_server/static/img/success.webm
slow_start_rewatch/http_server/templates/access_denied.html
slow_start_rewatch/http_server/templates/authorization_error.html
slow_start_rewatch/http_server/templates/base.html
slow_start_rewatch/http_server/templates/http_error.html
slow_start_rewatch/http_server/templates/success.html
slow_start_rewatch/post.py
slow_start_rewatch/post_helper.py
slow_start_rewatch/py.typed
slow_start_rewatch/reddit/__init__.py
slow_start_rewatch/reddit/oauth_helper.py
slow_start_rewatch/reddit/post_image.py
slow_start_rewatch-0.2.4.dist-info/entry_points.txt
slow_start_rewatch-0.2.4.dist-info/LICENSE
slow_start_rewatch-0.2.4.dist-info/WHEEL
slow_start_rewatch-0.2.4.dist-info/METADATA
slow_start_rewatch-0.2.4.dist-info/RECORD
