Metadata-Version: 2.1
Name: slow-start-rewatch
Version: 0.2.4
Summary: Make cute things happen!
Home-page: https://github.com/slow-start-fans/slow-start-rewatch
License: MIT
Requires-Python: >=3.6,<4.0
Classifier: Development Status :: 3 - Alpha
Classifier: Intended Audience :: Developers
Classifier: License :: OSI Approved :: MIT License
Classifier: Operating System :: OS Independent
Classifier: Programming Language :: Python :: 3
Classifier: Programming Language :: Python :: 3.6
Classifier: Programming Language :: Python :: 3.7
Classifier: Programming Language :: Python :: 3.8
Classifier: Topic :: Software Development :: Libraries :: Python Modules
Requires-Dist: anyconfig (>=0.9.11,<0.10.0)
Requires-Dist: click (>=7.1.2,<8.0.0)
Requires-Dist: colorama (>=0.4.3,<0.5.0)
Requires-Dist: flask (>=1.1.2,<2.0.0)
Requires-Dist: importlib_metadata (>=1.6.0,<2.0.0)
Requires-Dist: praw (>=7.0.0,<8.0.0)
Requires-Dist: ruamel.yaml (>=0.16.10,<0.17.0)
Requires-Dist: scalpl (>=0.4.1,<0.5.0)
Requires-Dist: structlog (>=20.1.0,<21.0.0)
Project-URL: Repository, https://github.com/slow-start-fans/slow-start-rewatch
